contact_us_tools/__init__.py
contact_us_tools/admin.py
contact_us_tools/apps.py
contact_us_tools/forms.py
contact_us_tools/models.py
contact_us_tools/tests.py
contact_us_tools/views.py
contact_us_tools/migrations/__init__.py
contact_us_tools/templates/contact_us_tools/email.html
contact_us_tools/templates/contact_us_tools/email.txt
django_contact_us_tools-0.1.3.dist-info/licenses/LICENSE
django_contact_us_tools-0.1.3.dist-info/METADATA
django_contact_us_tools-0.1.3.dist-info/WHEEL
django_contact_us_tools-0.1.3.dist-info/top_level.txt
django_contact_us_tools-0.1.3.dist-info/RECORD
